{"㣺":{"english_summary":"(variant of 心) the heart, the moral nature, the mind, the affections, intention, the radical on left side of the character","has_character":1,"has_word":0,"hsk_min_level":null,"primary_jyutping":"sam1","primary_pinyin":"xīn","simplified":null,"text":"㣺","traditional":null},"䅛":{"english_summary":"husks of rice; rice bran or chaff","has_character":1,"has_word":0,"hsk_min_level":null,"primary_jyutping":"coeng1","primary_pinyin":"chāng","simplified":null,"text":"䅛","traditional":null},"五彩缤纷":{"english_summary":"all the colors in profusion (idiom); a garish display","has_character":0,"has_word":1,"hsk_min_level":null,"primary_jyutping":null,"primary_pinyin":"wǔ cǎi bīn fēn","simplified":"五彩缤纷","text":"五彩缤纷","traditional":"五彩繽紛"},"交易所交易基金":{"english_summary":"exchange-traded fund (ETF)","has_character":0,"has_word":1,"hsk_min_level":null,"primary_jyutping":null,"primary_pinyin":"jiāo yì suǒ jiāo yì jī jīn","simplified":"交易所交易基金","text":"交易所交易基金","traditional":"交易所交易基金"},"仇人":{"english_summary":"foe; one's personal enemy","has_character":0,"has_word":1,"hsk_min_level":null,"primary_jyutping":null,"primary_pinyin":"chóu rén","simplified":"仇人","text":"仇人","traditional":"仇人"},"伊妹兒":{"english_summary":"(loanword) email","has_character":0,"has_word":1,"hsk_min_level":null,"primary_jyutping":null,"primary_pinyin":"yī mèi r","simplified":"伊妹儿","text":"伊妹兒","traditional":"伊妹兒"},"俄勒冈州":{"english_summary":"Oregon","has_character":0,"has_word":1,"hsk_min_level":null,"primary_jyutping":null,"primary_pinyin":"e lè gāng zhōu","simplified":"俄勒冈州","text":"俄勒冈州","traditional":"俄勒岡州"},"偿还":{"english_summary":"to repay; to reimburse","has_character":0,"has_word":1,"hsk_min_level":6,"primary_jyutping":null,"primary_pinyin":"cháng huán","simplified":"偿还","text":"偿还","traditional":"償還"},"出老千":{"english_summary":"to cheat (in gambling)","has_character":0,"has_word":1,"hsk_min_level":null,"primary_jyutping":null,"primary_pinyin":"chū lǎo qiān","simplified":"出老千","text":"出老千","traditional":"出老千"},"北苑":{"english_summary":"Beiyuan neighborhood of Beijing","has_character":0,"has_word":1,"hsk_min_level":null,"primary_jyutping":null,"primary_pinyin":"běi yuàn","simplified":"北苑","text":"北苑","traditional":"北苑"},"华盛顿时报":{"english_summary":"Washington Times (newspaper)","has_character":0,"has_word":1,"hsk_min_level":null,"primary_jyutping":null,"primary_pinyin":"huá shèng dùn shí bào","simplified":"华盛顿时报","text":"华盛顿时报","traditional":"華盛頓時報"},"反攻":{"english_summary":"to counterattack; a counteroffensive","has_character":0,"has_word":1,"hsk_min_level":null,"primary_jyutping":null,"primary_pinyin":"fǎn gōng","simplified":"反攻","text":"反攻","traditional":"反攻"},"咯":{"english_summary":"final particle","has_character":1,"has_word":1,"hsk_min_level":null,"primary_jyutping":"gok3","primary_pinyin":"gē","simplified":"咯","text":"咯","traditional":"咯"},"喜喜歡歡":{"english_summary":"happily","has_character":0,"has_word":1,"hsk_min_level":null,"primary_jyutping":null,"primary_pinyin":"xǐ xǐ huān huān","simplified":"喜喜欢欢","text":"喜喜歡歡","traditional":"喜喜歡歡"},"失憶":{"english_summary":"to lose one's memory","has_character":0,"has_word":1,"hsk_min_level":null,"primary_jyutping":null,"primary_pinyin":"shī yì","simplified":"失忆","text":"失憶","traditional":"失憶"},"安道爾":{"english_summary":"Andorra","has_character":0,"has_word":1,"hsk_min_level":null,"primary_jyutping":null,"primary_pinyin":"an dào ěr","simplified":"安道尔","text":"安道爾","traditional":"安道爾"},"家家戶戶":{"english_summary":"each and every family (idiom); every household","has_character":0,"has_word":1,"hsk_min_level":null,"primary_jyutping":null,"primary_pinyin":"jiā jiā hù hù","simplified":"家家户户","text":"家家戶戶","traditional":"家家戶戶"},"巢穴":{"english_summary":"lair; nest; den","has_character":0,"has_word":1,"hsk_min_level":null,"primary_jyutping":null,"primary_pinyin":"cháo xué","simplified":"巢穴","text":"巢穴","traditional":"巢穴"},"想當然耳":{"english_summary":"variant of 想當然爾|想当然尔[xiang3 dang1 ran2 er3]","has_character":0,"has_word":1,"hsk_min_level":null,"primary_jyutping":null,"primary_pinyin":"xiǎng dāng rán ěr","simplified":"想当然耳","text":"想當然耳","traditional":"想當然耳"},"攮":{"english_summary":"to fend off; to stab","has_character":1,"has_word":1,"hsk_min_level":null,"primary_jyutping":"nong5","primary_pinyin":"nǎng","simplified":"攮","text":"攮","traditional":"攮"},"教學法":{"english_summary":"teaching method; pedagogy","has_character":0,"has_word":1,"hsk_min_level":null,"primary_jyutping":null,"primary_pinyin":"jiào xué fǎ","simplified":"教学法","text":"教學法","traditional":"教學法"},"斯洛文尼亚":{"english_summary":"Slovenia","has_character":0,"has_word":1,"hsk_min_level":null,"primary_jyutping":null,"primary_pinyin":"sī luò wén ní yà","simplified":"斯洛文尼亚","text":"斯洛文尼亚","traditional":"斯洛文尼亞"},"无穷小":{"english_summary":"(math.) infinitesimal; infinitely small","has_character":0,"has_word":1,"hsk_min_level":null,"primary_jyutping":null,"primary_pinyin":"wú qióng xiǎo","simplified":"无穷小","text":"无穷小","traditional":"無窮小"},"时政":{"english_summary":"current politics; political situation of the time","has_character":0,"has_word":1,"hsk_min_level":null,"primary_jyutping":null,"primary_pinyin":"shí zhèng","simplified":"时政","text":"时政","traditional":"時政"},"東方明珠電視塔":{"english_summary":"Oriental Pearl Television Tower","has_character":0,"has_word":1,"hsk_min_level":null,"primary_jyutping":null,"primary_pinyin":"dōng fāng míng zhū diàn shì tǎ","simplified":"东方明珠电视塔","text":"東方明珠電視塔","traditional":"東方明珠電視塔"},"树碑立传":{"english_summary":"lit. to erect a stele and write a biography (idiom); to monumentalize; to glorify","has_character":0,"has_word":1,"hsk_min_level":null,"primary_jyutping":null,"primary_pinyin":"shù bēi lì zhuàn","simplified":"树碑立传","text":"树碑立传","traditional":"樹碑立傳"},"波斑鴇":{"english_summary":"(bird species of China) MacQueen's bustard (Chlamydotis macqueenii)","has_character":0,"has_word":1,"hsk_min_level":null,"primary_jyutping":null,"primary_pinyin":"bō bān bǎo","simplified":"波斑鸨","text":"波斑鴇","traditional":"波斑鴇"},"活物":{"english_summary":"living animals","has_character":0,"has_word":1,"hsk_min_level":null,"primary_jyutping":null,"primary_pinyin":"huó wù","simplified":"活物","text":"活物","traditional":"活物"},"混合毒剂":{"english_summary":"tactical mixture of chemical agents","has_character":0,"has_word":1,"hsk_min_level":null,"primary_jyutping":null,"primary_pinyin":"hùn hé dú jì","simplified":"混合毒剂","text":"混合毒剂","traditional":"混合毒劑"},"潮汐電站":{"english_summary":"tidal power station","has_character":0,"has_word":1,"hsk_min_level":null,"primary_jyutping":null,"primary_pinyin":"cháo xī diàn zhàn","simplified":"潮汐电站","text":"潮汐電站","traditional":"潮汐電站"},"潸然淚下":{"english_summary":"to shed silent tears (idiom)","has_character":0,"has_word":1,"hsk_min_level":null,"primary_jyutping":null,"primary_pinyin":"shān rán lèi xià","simplified":"潸然泪下","text":"潸然淚下","traditional":"潸然淚下"},"牙石":{"english_summary":"dental calculus; tartar","has_character":0,"has_word":1,"hsk_min_level":null,"primary_jyutping":null,"primary_pinyin":"yá shí","simplified":"牙石","text":"牙石","traditional":"牙石"},"申请":{"english_summary":"to apply for sth; application form (CL:份[fen4])","has_character":0,"has_word":1,"hsk_min_level":4,"primary_jyutping":null,"primary_pinyin":"shēn qǐng","simplified":"申请","text":"申请","traditional":"申請"},"發揚光大":{"english_summary":"to develop and promote; to carry forward; to bring to great height of development","has_character":0,"has_word":1,"hsk_min_level":null,"primary_jyutping":null,"primary_pinyin":"fā yáng guāng dà","simplified":"发扬光大","text":"發揚光大","traditional":"發揚光大"},"相繼":{"english_summary":"in succession; following closely","has_character":0,"has_word":1,"hsk_min_level":null,"primary_jyutping":null,"primary_pinyin":"xiāng jì","simplified":"相继","text":"相繼","traditional":"相繼"},"硯室":{"english_summary":"case for an ink slab","has_character":0,"has_word":1,"hsk_min_level":null,"primary_jyutping":null,"primary_pinyin":"yàn shì","simplified":"砚室","text":"硯室","traditional":"硯室"},"秪":{"english_summary":"only, merely","has_character":1,"has_word":0,"hsk_min_level":null,"primary_jyutping":"zi1","primary_pinyin":"zhī","simplified":null,"text":"秪","traditional":null},"稍候":{"english_summary":"to wait a moment","has_character":0,"has_word":1,"hsk_min_level":null,"primary_jyutping":null,"primary_pinyin":"shāo hòu","simplified":"稍候","text":"稍候","traditional":"稍候"},"筵席捐":{"english_summary":"tax on a banquet or feast","has_character":0,"has_word":1,"hsk_min_level":null,"primary_jyutping":null,"primary_pinyin":"yán xí juān","simplified":"筵席捐","text":"筵席捐","traditional":"筵席捐"},"累趴":{"english_summary":"tired to the point of dropping","has_character":0,"has_word":1,"hsk_min_level":null,"primary_jyutping":null,"primary_pinyin":"lèi pā","simplified":"累趴","text":"累趴","traditional":"累趴"},"舟山":{"english_summary":"see 舟山市[Zhou1 shan1 Shi4]","has_character":0,"has_word":1,"hsk_min_level":null,"primary_jyutping":null,"primary_pinyin":"zhōu shān","simplified":"舟山","text":"舟山","traditional":"舟山"},"航線":{"english_summary":"air or shipping route","has_character":0,"has_word":1,"hsk_min_level":null,"primary_jyutping":null,"primary_pinyin":"háng xiàn","simplified":"航线","text":"航線","traditional":"航線"},"苍":{"english_summary":"blue; green","has_character":1,"has_word":1,"hsk_min_level":6,"primary_jyutping":"cong1","primary_pinyin":"cāng","simplified":"苍","text":"苍","traditional":"蒼"},"號子":{"english_summary":"work chant; prison cell; type","has_character":0,"has_word":1,"hsk_min_level":null,"primary_jyutping":null,"primary_pinyin":"hào zi","simplified":"号子","text":"號子","traditional":"號子"},"裝備":{"english_summary":"equipment; to equip; to outfit","has_character":0,"has_word":1,"hsk_min_level":6,"primary_jyutping":null,"primary_pinyin":"zhuāng bèi","simplified":"装备","text":"裝備","traditional":"裝備"},"西屯区":{"english_summary":"Xitun District of Taichung, Taiwan","has_character":0,"has_word":1,"hsk_min_level":null,"primary_jyutping":null,"primary_pinyin":"xī tún qū","simplified":"西屯区","text":"西屯区","traditional":"西屯區"},"贼眉鼠眼":{"english_summary":"shifty-eyed; crafty-looking (idiom)","has_character":0,"has_word":1,"hsk_min_level":null,"primary_jyutping":null,"primary_pinyin":"zéi méi shǔ yǎn","simplified":"贼眉鼠眼","text":"贼眉鼠眼","traditional":"賊眉鼠眼"},"轮转机":{"english_summary":"merry-go-round","has_character":0,"has_word":1,"hsk_min_level":null,"primary_jyutping":null,"primary_pinyin":"lún zhuǎn jī","simplified":"轮转机","text":"轮转机","traditional":"輪轉機"},"通識培訓":{"english_summary":"general culture","has_character":0,"has_word":1,"hsk_min_level":null,"primary_jyutping":null,"primary_pinyin":"tōng shí péi xùn","simplified":"通识培训","text":"通識培訓","traditional":"通識培訓"},"鉛錘":{"english_summary":"bob of a plumbline","has_character":0,"has_word":1,"hsk_min_level":null,"primary_jyutping":null,"primary_pinyin":"qiān chuí","simplified":"铅锤","text":"鉛錘","traditional":"鉛錘"},"铅锤":{"english_summary":"bob of a plumbline","has_character":0,"has_word":1,"hsk_min_level":null,"primary_jyutping":null,"primary_pinyin":"qiān chuí","simplified":"铅锤","text":"铅锤","traditional":"鉛錘"},"開放系統":{"english_summary":"open system","has_character":0,"has_word":1,"hsk_min_level":null,"primary_jyutping":null,"primary_pinyin":"kāi fàng xì tǒng","simplified":"开放系统","text":"開放系統","traditional":"開放系統"},"阿比西尼亚":{"english_summary":"Abyssinia, historical name of Ethiopia","has_character":0,"has_word":1,"hsk_min_level":null,"primary_jyutping":null,"primary_pinyin":"a bǐ xī ní yà","simplified":"阿比西尼亚","text":"阿比西尼亚","traditional":"阿比西尼亞"},"除開":{"english_summary":"besides; except; to get rid of (sb)","has_character":0,"has_word":1,"hsk_min_level":null,"primary_jyutping":null,"primary_pinyin":"chú kāi","simplified":"除开","text":"除開","traditional":"除開"},"雲消霧散":{"english_summary":"the clouds melt and the mists disperse (idiom); to clear up; to vanish into thin air","has_character":0,"has_word":1,"hsk_min_level":null,"primary_jyutping":null,"primary_pinyin":"yún xiāo wù sàn","simplified":"云消雾散","text":"雲消霧散","traditional":"雲消霧散"},"餘波":{"english_summary":"aftermath; repercussions; fallout","has_character":0,"has_word":1,"hsk_min_level":null,"primary_jyutping":null,"primary_pinyin":"yú bō","simplified":"余波","text":"餘波","traditional":"餘波"},"馟":{"english_summary":"fragrant","has_character":1,"has_word":0,"hsk_min_level":null,"primary_jyutping":"tou4","primary_pinyin":"tú","simplified":null,"text":"馟","traditional":null},"高速":{"english_summary":"high speed; expressway (abbr. for 高速公路[gao1 su4 gong1 lu4])","has_character":0,"has_word":1,"hsk_min_level":5,"primary_jyutping":null,"primary_pinyin":"gāo sù","simplified":"高速","text":"高速","traditional":"高速"},"鸡飞蛋打":{"english_summary":"the chicken has flown the coop and the eggs are broken; a dead loss (idiom)","has_character":0,"has_word":1,"hsk_min_level":null,"primary_jyutping":null,"primary_pinyin":"jī fēi dàn dǎ","simplified":"鸡飞蛋打","text":"鸡飞蛋打","traditional":"雞飛蛋打"},"𠸦":{"english_summary":null,"has_character":1,"has_word":0,"hsk_min_level":null,"primary_jyutping":null,"primary_pinyin":null,"simplified":null,"text":"𠸦","traditional":null},"𡡨":{"english_summary":null,"has_character":1,"has_word":0,"hsk_min_level":null,"primary_jyutping":null,"primary_pinyin":null,"simplified":null,"text":"𡡨","traditional":null},"𢲆":{"english_summary":null,"has_character":1,"has_word":0,"hsk_min_level":null,"primary_jyutping":null,"primary_pinyin":null,"simplified":null,"text":"𢲆","traditional":null},"𣯈":{"english_summary":null,"has_character":1,"has_word":0,"hsk_min_level":null,"primary_jyutping":null,"primary_pinyin":null,"simplified":null,"text":"𣯈","traditional":null},"𤎔":{"english_summary":null,"has_character":1,"has_word":0,"hsk_min_level":null,"primary_jyutping":null,"primary_pinyin":null,"simplified":null,"text":"𤎔","traditional":null},"𥔇":{"english_summary":null,"has_character":1,"has_word":0,"hsk_min_level":null,"primary_jyutping":null,"primary_pinyin":"kōng","simplified":null,"text":"𥔇","traditional":null},"𦛉":{"english_summary":null,"has_character":1,"has_word":0,"hsk_min_level":null,"primary_jyutping":null,"primary_pinyin":null,"simplified":null,"text":"𦛉","traditional":null},"𧟜":{"english_summary":null,"has_character":1,"has_word":0,"hsk_min_level":null,"primary_jyutping":null,"primary_pinyin":"jì","simplified":null,"text":"𧟜","traditional":null},"𨆠":{"english_summary":null,"has_character":1,"has_word":0,"hsk_min_level":null,"primary_jyutping":null,"primary_pinyin":null,"simplified":null,"text":"𨆠","traditional":null},"𩨷":{"english_summary":null,"has_character":1,"has_word":0,"hsk_min_level":null,"primary_jyutping":null,"primary_pinyin":"quē","simplified":null,"text":"𩨷","traditional":null},"𪿹":{"english_summary":null,"has_character":1,"has_word":0,"hsk_min_level":null,"primary_jyutping":null,"primary_pinyin":null,"simplified":null,"text":"𪿹","traditional":null},"𫸅":{"english_summary":null,"has_character":1,"has_word":0,"hsk_min_level":null,"primary_jyutping":null,"primary_pinyin":null,"simplified":null,"text":"𫸅","traditional":null},"𬆴":{"english_summary":null,"has_character":1,"has_word":0,"hsk_min_level":null,"primary_jyutping":null,"primary_pinyin":null,"simplified":null,"text":"𬆴","traditional":null},"𬻿":{"english_summary":null,"has_character":1,"has_word":0,"hsk_min_level":null,"primary_jyutping":null,"primary_pinyin":null,"simplified":null,"text":"𬻿","traditional":null},"𭮁":{"english_summary":null,"has_character":1,"has_word":0,"hsk_min_level":null,"primary_jyutping":null,"primary_pinyin":null,"simplified":null,"text":"𭮁","traditional":null},"𮏍":{"english_summary":null,"has_character":1,"has_word":0,"hsk_min_level":null,"primary_jyutping":null,"primary_pinyin":null,"simplified":null,"text":"𮏍","traditional":null},"𰔂":{"english_summary":null,"has_character":1,"has_word":0,"hsk_min_level":null,"primary_jyutping":null,"primary_pinyin":null,"simplified":null,"text":"𰔂","traditional":null},"𱞵":{"english_summary":null,"has_character":1,"has_word":0,"hsk_min_level":null,"primary_jyutping":null,"primary_pinyin":null,"simplified":null,"text":"𱞵","traditional":null}}