{"㦬":{"english_summary":"ashamed; abashed; mortified; humiliated, few; little scarce; rare","has_character":1,"has_word":0,"hsk_min_level":null,"primary_jyutping":"lo5","primary_pinyin":"luǒ","simplified":null,"text":"㦬","traditional":null},"䜍":{"english_summary":"sweet; artful words","has_character":1,"has_word":0,"hsk_min_level":null,"primary_jyutping":"liu4","primary_pinyin":"liáo","simplified":null,"text":"䜍","traditional":null},"上方寶劍":{"english_summary":"imperial sword (giving bearer plenipotentiary powers); imperial Chinese version of 007 licensed to kill","has_character":0,"has_word":1,"hsk_min_level":null,"primary_jyutping":null,"primary_pinyin":"shàng fāng bǎo jiàn","simplified":"上方宝剑","text":"上方寶劍","traditional":"上方寶劍"},"书稿":{"english_summary":"manuscript of a book","has_character":0,"has_word":1,"hsk_min_level":null,"primary_jyutping":null,"primary_pinyin":"shū gǎo","simplified":"书稿","text":"书稿","traditional":"書稿"},"伶鼬":{"english_summary":"weasel; Mustela nivalis (zoology)","has_character":0,"has_word":1,"hsk_min_level":null,"primary_jyutping":null,"primary_pinyin":"líng yòu","simplified":"伶鼬","text":"伶鼬","traditional":"伶鼬"},"全歼":{"english_summary":"to annihilate; to wipe out completely; to exterminate","has_character":0,"has_word":1,"hsk_min_level":null,"primary_jyutping":null,"primary_pinyin":"quán jiān","simplified":"全歼","text":"全歼","traditional":"全殲"},"出氣":{"english_summary":"to vent one's anger; to breathe out; to exhale","has_character":0,"has_word":1,"hsk_min_level":null,"primary_jyutping":null,"primary_pinyin":"chū qì","simplified":"出气","text":"出氣","traditional":"出氣"},"化學性質":{"english_summary":"chemical property","has_character":0,"has_word":1,"hsk_min_level":null,"primary_jyutping":null,"primary_pinyin":"huà xué xìng zhì","simplified":"化学性质","text":"化學性質","traditional":"化學性質"},"卖春":{"english_summary":"to engage in prostitution","has_character":0,"has_word":1,"hsk_min_level":null,"primary_jyutping":null,"primary_pinyin":"mài chūn","simplified":"卖春","text":"卖春","traditional":"賣春"},"司馬懿":{"english_summary":"Sima Yi (179-251), warlord under Cao Cao and subsequently founder of the Jin dynasty","has_character":0,"has_word":1,"hsk_min_level":null,"primary_jyutping":null,"primary_pinyin":"sī mǎ yì","simplified":"司马懿","text":"司馬懿","traditional":"司馬懿"},"吃公糧":{"english_summary":"to be on the government payroll","has_character":0,"has_word":1,"hsk_min_level":null,"primary_jyutping":null,"primary_pinyin":"chī gōng liáng","simplified":"吃公粮","text":"吃公糧","traditional":"吃公糧"},"啟":{"english_summary":"open; begin","has_character":1,"has_word":1,"hsk_min_level":5,"primary_jyutping":"kai2","primary_pinyin":"qǐ","simplified":"启","text":"啟","traditional":"啟"},"图形卡":{"english_summary":"graphics card","has_character":0,"has_word":1,"hsk_min_level":null,"primary_jyutping":null,"primary_pinyin":"tú xíng kǎ","simplified":"图形卡","text":"图形卡","traditional":"圖形卡"},"增高":{"english_summary":"to heighten; to raise; to increase","has_character":0,"has_word":1,"hsk_min_level":null,"primary_jyutping":null,"primary_pinyin":"zēng gāo","simplified":"增高","text":"增高","traditional":"增高"},"复用":{"english_summary":"to reuse","has_character":0,"has_word":1,"hsk_min_level":null,"primary_jyutping":null,"primary_pinyin":"fù yòng","simplified":"复用","text":"复用","traditional":"複用"},"外孙女儿":{"english_summary":"granddaughter (one's daughter's daughter)","has_character":0,"has_word":1,"hsk_min_level":null,"primary_jyutping":null,"primary_pinyin":"wài sūn nǚ r","simplified":"外孙女儿","text":"外孙女儿","traditional":"外孫女兒"},"天尊":{"english_summary":"(honorific appellation of a deity)","has_character":0,"has_word":1,"hsk_min_level":null,"primary_jyutping":null,"primary_pinyin":"tiān zūn","simplified":"天尊","text":"天尊","traditional":"天尊"},"太空人":{"english_summary":"astronaut","has_character":0,"has_word":1,"hsk_min_level":null,"primary_jyutping":null,"primary_pinyin":"tài kōng rén","simplified":"太空人","text":"太空人","traditional":"太空人"},"干货":{"english_summary":"dried food (including dried fruits, mushrooms and seafoods such as shrimp and abalone); (fig.) (coll.) knowledge presented in readily assimilable form; just what you want to know: no more, no less (no padding 水分[shui3 fen4])","has_character":0,"has_word":1,"hsk_min_level":null,"primary_jyutping":null,"primary_pinyin":"gān huò","simplified":"干货","text":"干货","traditional":"乾貨"},"感發":{"english_summary":"to move and inspire","has_character":0,"has_word":1,"hsk_min_level":null,"primary_jyutping":null,"primary_pinyin":"gǎn fā","simplified":"感发","text":"感發","traditional":"感發"},"憑什麼":{"english_summary":"(spoken) why?; for which reason?","has_character":0,"has_word":1,"hsk_min_level":null,"primary_jyutping":null,"primary_pinyin":"píng shén me","simplified":"凭什么","text":"憑什麼","traditional":"憑什麼"},"所":{"english_summary":"place, location; numerary adjunct","has_character":1,"has_word":1,"hsk_min_level":2,"primary_jyutping":"so2","primary_pinyin":"suǒ","simplified":"所","text":"所","traditional":"所"},"旧友":{"english_summary":"old friend","has_character":0,"has_word":1,"hsk_min_level":null,"primary_jyutping":null,"primary_pinyin":"jiù yǒu","simplified":"旧友","text":"旧友","traditional":"舊友"},"星期四":{"english_summary":"Thursday","has_character":0,"has_word":1,"hsk_min_level":null,"primary_jyutping":null,"primary_pinyin":"xīng qī sì","simplified":"星期四","text":"星期四","traditional":"星期四"},"月牙形":{"english_summary":"crescent","has_character":0,"has_word":1,"hsk_min_level":null,"primary_jyutping":null,"primary_pinyin":"yuè yá xíng","simplified":"月牙形","text":"月牙形","traditional":"月牙形"},"札達":{"english_summary":"see 札達縣|札达县[Zha2 da2 Xian4]","has_character":0,"has_word":1,"hsk_min_level":null,"primary_jyutping":null,"primary_pinyin":"zhá dá","simplified":"札达","text":"札達","traditional":"札達"},"桓玄":{"english_summary":"Huan Xuan (369-404), general involved in the break-up of Eastern Jin","has_character":0,"has_word":1,"hsk_min_level":null,"primary_jyutping":null,"primary_pinyin":"huán xuán","simplified":"桓玄","text":"桓玄","traditional":"桓玄"},"歉疚":{"english_summary":"remorseful; guilt-ridden","has_character":0,"has_word":1,"hsk_min_level":null,"primary_jyutping":null,"primary_pinyin":"qiàn jiù","simplified":"歉疚","text":"歉疚","traditional":"歉疚"},"水磨石":{"english_summary":"terrazzo","has_character":0,"has_word":1,"hsk_min_level":null,"primary_jyutping":null,"primary_pinyin":"shuǐ mó shí","simplified":"水磨石","text":"水磨石","traditional":"水磨石"},"浸禮會":{"english_summary":"Baptists","has_character":0,"has_word":1,"hsk_min_level":null,"primary_jyutping":null,"primary_pinyin":"jìn lǐ huì","simplified":"浸礼会","text":"浸禮會","traditional":"浸禮會"},"游船":{"english_summary":"pleasure boat; cruise ship","has_character":0,"has_word":1,"hsk_min_level":null,"primary_jyutping":null,"primary_pinyin":"yóu chuán","simplified":"游船","text":"游船","traditional":"遊船"},"烹煮":{"english_summary":"to cook; to boil","has_character":0,"has_word":1,"hsk_min_level":null,"primary_jyutping":null,"primary_pinyin":"pēng zhǔ","simplified":"烹煮","text":"烹煮","traditional":"烹煮"},"生產率":{"english_summary":"productivity; efficiency of production","has_character":0,"has_word":1,"hsk_min_level":null,"primary_jyutping":null,"primary_pinyin":"shēng chǎn lǜ","simplified":"生产率","text":"生產率","traditional":"生產率"},"畏罪自杀":{"english_summary":"to commit suicide to escape punishment","has_character":0,"has_word":1,"hsk_min_level":null,"primary_jyutping":null,"primary_pinyin":"wèi zuì zì shā","simplified":"畏罪自杀","text":"畏罪自杀","traditional":"畏罪自殺"},"直播":{"english_summary":"(TV, radio) to broadcast live; live broadcast; (Internet) to livestream","has_character":0,"has_word":1,"hsk_min_level":6,"primary_jyutping":null,"primary_pinyin":"zhí bō","simplified":"直播","text":"直播","traditional":"直播"},"短視頻":{"english_summary":"short video; video clip","has_character":0,"has_word":1,"hsk_min_level":null,"primary_jyutping":null,"primary_pinyin":"duǎn shì pín","simplified":"短视频","text":"短視頻","traditional":"短視頻"},"碜":{"english_summary":"gritty","has_character":1,"has_word":1,"hsk_min_level":null,"primary_jyutping":"cam2","primary_pinyin":"chěn","simplified":"碜","text":"碜","traditional":"磣"},"符牌":{"english_summary":"a talisman or lucky charm","has_character":0,"has_word":1,"hsk_min_level":null,"primary_jyutping":null,"primary_pinyin":"fú pái","simplified":"符牌","text":"符牌","traditional":"符牌"},"筚门闺窦":{"english_summary":"wicker door, hole window (idiom); fig. wretched hovel; living in poverty","has_character":0,"has_word":1,"hsk_min_level":null,"primary_jyutping":null,"primary_pinyin":"bì mén guī dòu","simplified":"筚门闺窦","text":"筚门闺窦","traditional":"篳門閨竇"},"结巴":{"english_summary":"to stutter","has_character":0,"has_word":1,"hsk_min_level":null,"primary_jyutping":null,"primary_pinyin":"jiē ba","simplified":"结巴","text":"结巴","traditional":"結巴"},"脖梗子":{"english_summary":"variant of 脖頸子|脖颈子[bo2 geng3 zi5]","has_character":0,"has_word":1,"hsk_min_level":null,"primary_jyutping":null,"primary_pinyin":"bó gěng zi","simplified":"脖梗子","text":"脖梗子","traditional":"脖梗子"},"舉目":{"english_summary":"to look; to raise one's eyes","has_character":0,"has_word":1,"hsk_min_level":null,"primary_jyutping":null,"primary_pinyin":"jǔ mù","simplified":"举目","text":"舉目","traditional":"舉目"},"舽":{"english_summary":null,"has_character":1,"has_word":0,"hsk_min_level":null,"primary_jyutping":"fung4","primary_pinyin":"páng","simplified":null,"text":"舽","traditional":null},"薩達姆·侯賽因":{"english_summary":"Saddam Hussein","has_character":0,"has_word":1,"hsk_min_level":null,"primary_jyutping":null,"primary_pinyin":"sà dá mǔ hóu sài yīn","simplified":"萨达姆·侯赛因","text":"薩達姆·侯賽因","traditional":"薩達姆·侯賽因"},"超物理":{"english_summary":"surpassing the physical world; metaphysical","has_character":0,"has_word":1,"hsk_min_level":null,"primary_jyutping":null,"primary_pinyin":"chāo wù lǐ","simplified":"超物理","text":"超物理","traditional":"超物理"},"转弯抹角":{"english_summary":"see 拐彎抹角|拐弯抹角[guai3 wan1 mo4 jiao3]","has_character":0,"has_word":1,"hsk_min_level":null,"primary_jyutping":null,"primary_pinyin":"zhuǎn wān mò jiǎo","simplified":"转弯抹角","text":"转弯抹角","traditional":"轉彎抹角"},"釋手":{"english_summary":"to let go; to loosen one's grip; to put sth down","has_character":0,"has_word":1,"hsk_min_level":null,"primary_jyutping":null,"primary_pinyin":"shì shǒu","simplified":"释手","text":"釋手","traditional":"釋手"},"鎮台":{"english_summary":"garrison commander (old)","has_character":0,"has_word":1,"hsk_min_level":null,"primary_jyutping":null,"primary_pinyin":"zhèn tái","simplified":"镇台","text":"鎮台","traditional":"鎮台"},"闺房":{"english_summary":"lady's chamber; boudoir; harem","has_character":0,"has_word":1,"hsk_min_level":null,"primary_jyutping":null,"primary_pinyin":"guī fáng","simplified":"闺房","text":"闺房","traditional":"閨房"},"陨石":{"english_summary":"meteorite; aerolite; CL:塊|块[kuai4],顆|颗[ke1]","has_character":0,"has_word":1,"hsk_min_level":null,"primary_jyutping":null,"primary_pinyin":"yǔn shí","simplified":"陨石","text":"陨石","traditional":"隕石"},"饶命":{"english_summary":"to spare sb's life","has_character":0,"has_word":1,"hsk_min_level":null,"primary_jyutping":null,"primary_pinyin":"ráo mìng","simplified":"饶命","text":"饶命","traditional":"饒命"},"高聳入雲":{"english_summary":"tall and erect, reaching through the clouds (idiom); used to describe tall mountain or skyscraper","has_character":0,"has_word":1,"hsk_min_level":null,"primary_jyutping":null,"primary_pinyin":"gāo sǒng rù yún","simplified":"高耸入云","text":"高聳入雲","traditional":"高聳入雲"},"輦":{"english_summary":"a hand-cart; to transport by carriage","has_character":1,"has_word":0,"hsk_min_level":null,"primary_jyutping":"lin5","primary_pinyin":"niǎn","simplified":null,"text":"輦","traditional":null},"𠵈":{"english_summary":"(Cant.) to suck or chew without using the teeth","has_character":1,"has_word":0,"hsk_min_level":null,"primary_jyutping":"mui2","primary_pinyin":null,"simplified":null,"text":"𠵈","traditional":null},"𡤚":{"english_summary":null,"has_character":1,"has_word":0,"hsk_min_level":null,"primary_jyutping":null,"primary_pinyin":null,"simplified":null,"text":"𡤚","traditional":null},"𢿨":{"english_summary":null,"has_character":1,"has_word":0,"hsk_min_level":null,"primary_jyutping":null,"primary_pinyin":null,"simplified":null,"text":"𢿨","traditional":null},"𣪺":{"english_summary":"gauze","has_character":1,"has_word":0,"hsk_min_level":null,"primary_jyutping":"huk6","primary_pinyin":null,"simplified":null,"text":"𣪺","traditional":null},"𤳶":{"english_summary":null,"has_character":1,"has_word":0,"hsk_min_level":null,"primary_jyutping":null,"primary_pinyin":null,"simplified":null,"text":"𤳶","traditional":null},"𥓧":{"english_summary":null,"has_character":1,"has_word":0,"hsk_min_level":null,"primary_jyutping":null,"primary_pinyin":null,"simplified":null,"text":"𥓧","traditional":null},"𦘹":{"english_summary":null,"has_character":1,"has_word":0,"hsk_min_level":null,"primary_jyutping":null,"primary_pinyin":"shàn","simplified":null,"text":"𦘹","traditional":null},"𨃂":{"english_summary":null,"has_character":1,"has_word":0,"hsk_min_level":null,"primary_jyutping":null,"primary_pinyin":null,"simplified":null,"text":"𨃂","traditional":null},"𩯗":{"english_summary":null,"has_character":1,"has_word":0,"hsk_min_level":null,"primary_jyutping":null,"primary_pinyin":null,"simplified":null,"text":"𩯗","traditional":null},"𪼩":{"english_summary":null,"has_character":1,"has_word":0,"hsk_min_level":null,"primary_jyutping":null,"primary_pinyin":null,"simplified":null,"text":"𪼩","traditional":null},"𫻥":{"english_summary":null,"has_character":1,"has_word":0,"hsk_min_level":null,"primary_jyutping":null,"primary_pinyin":null,"simplified":null,"text":"𫻥","traditional":null},"𬼯":{"english_summary":null,"has_character":1,"has_word":0,"hsk_min_level":null,"primary_jyutping":null,"primary_pinyin":null,"simplified":null,"text":"𬼯","traditional":null},"𭭡":{"english_summary":null,"has_character":1,"has_word":0,"hsk_min_level":null,"primary_jyutping":null,"primary_pinyin":null,"simplified":null,"text":"𭭡","traditional":null},"𮌽":{"english_summary":null,"has_character":1,"has_word":0,"hsk_min_level":null,"primary_jyutping":null,"primary_pinyin":null,"simplified":null,"text":"𮌽","traditional":null},"𰑤":{"english_summary":null,"has_character":1,"has_word":0,"hsk_min_level":null,"primary_jyutping":null,"primary_pinyin":null,"simplified":null,"text":"𰑤","traditional":null},"𱝕":{"english_summary":null,"has_character":1,"has_word":0,"hsk_min_level":null,"primary_jyutping":null,"primary_pinyin":null,"simplified":null,"text":"𱝕","traditional":null}}